{"pageProps":{"data":{"id":205,"url":"https://www.tvmaze.com/shows/205/graceland","name":"Graceland","type":"Scripted","language":"English","genres":["Drama","Action","Crime"],"status":"Ended","runtime":60,"averageRuntime":60,"premiered":"2013-06-06","ended":"2015-09-17","officialSite":"http://www.usanetwork.com/graceland","schedule":{"time":"22:00","days":["Thursday"]},"rating":{"average":7.2},"weight":81,"network":{"id":30,"name":"USA Network","country":{"name":"United States","code":"US","timezone":"America/New_York"},"officialSite":"https://www.usanetwork.com"},"webChannel":null,"dvdCountry":null,"externals":{"tvrage":32188,"thetvdb":260338,"imdb":"tt2393813"},"image":{"medium":"https://static.tvmaze.com/uploads/images/medium_portrait/54/137054.jpg","original":"https://static.tvmaze.com/uploads/images/original_untouched/54/137054.jpg"},"summary":"<p>Every year, the top graduates from the FBI Academy move from their classrooms at Quantico to their first assignments in the real world. For Agent Mike Warren, the dream has always been a post in Washington D.C. But the powers that be have other plans, and the young rookie is soon packing his bags for Graceland, a palatial beachfront mansion in Southern California that has become a cross-departmental boarding house for top undercover agents in the FBI, DEA and ICE.</p>","updated":1655183625,"_links":{"self":{"href":"https://api.tvmaze.com/shows/205"},"previousepisode":{"href":"https://api.tvmaze.com/episodes/201514"}}}},"__N_SSG":true}