{"pageProps":{"data":{"id":211,"url":"https://www.tvmaze.com/shows/211/666-park-avenue","name":"666 Park Avenue","type":"Scripted","language":"English","genres":["Drama","Mystery","Supernatural"],"status":"Ended","runtime":60,"averageRuntime":60,"premiered":"2012-09-30","ended":"2013-07-13","officialSite":null,"schedule":{"time":"21:00","days":["Saturday"]},"rating":{"average":6.6},"weight":86,"network":{"id":3,"name":"ABC","country":{"name":"United States","code":"US","timezone":"America/New_York"},"officialSite":"https://abc.com/"},"webChannel":null,"dvdCountry":null,"externals":{"tvrage":30744,"thetvdb":256204,"imdb":"tt2197797"},"image":{"medium":"https://static.tvmaze.com/uploads/images/medium_portrait/481/1204845.jpg","original":"https://static.tvmaze.com/uploads/images/original_untouched/481/1204845.jpg"},"summary":"<p><b>666 Park Avenue</b> is a supernatural drama based around the building of the same name run by Gavin Doran. The story follows a couple and mysterious happenings as they first move in to the establishment.</p>","updated":1697711124,"_links":{"self":{"href":"https://api.tvmaze.com/shows/211"},"previousepisode":{"href":"https://api.tvmaze.com/episodes/14089"}}}},"__N_SSG":true}